{
    "Friday": [
        {
            "room": "FD246", 
            "prof": "Petra Mehl", 
            "time": "08:00-17:15", 
            "name": "Interkulturelles Management", 
            "note": "(Gruppe II)", 
            "type": "HF:0"
        }, 
        {
            "room": "FA013", 
            "prof": "Petra Mehl", 
            "time": "08:00-17:15", 
            "name": "Interkulturelles Management", 
            "note": "(Gruppe II)", 
            "type": "HF:0"
        }, 
        {
            "room": "FA013", 
            "prof": "Petra Mehl", 
            "time": "08:00-17:15", 
            "name": "Interkulturelles Management", 
            "note": "(Gruppe I)", 
            "type": "HF:0"
        }, 
        {
            "room": "FA203", 
            "prof": "Petra Mehl", 
            "time": "09:45-17:15", 
            "name": "Personalentwicklung und beratung in globalen Unternehmen", 
            "type": "HF:0"
        }, 
        {
            "room": "FA203", 
            "prof": "Petra Mehl", 
            "time": "09:45-17:15", 
            "name": "Personalentwicklung und beratung in globalen Unternehmen", 
            "type": "HF:0"
        }, 
        {
            "room": "FA013", 
            "prof": "Dr. Robin M\u00fcller", 
            "time": "09:45-19:00", 
            "name": "Personalentwicklung und beratung in globalen Unternehmen", 
            "type": "HF:0"
        }, 
        {
            "room": "FA013", 
            "prof": "Dr. Robin M\u00fcller", 
            "time": "09:45-13:00", 
            "name": "Personalentwicklung und beratung in globalen Unternehmen", 
            "type": "HF:0"
        }, 
        {
            "desc": "Personalentwicklung und beratung in globalen Unternehmen\nBlockveranstaltung\nam 17.11.2012 von 08:00 bis 15:30", 
            "room": "FA203", 
            "prof": "Petra Mehl", 
            "time": "08:00-15:30", 
            "name": "Saturday", 
            "type": "HF:0"
        }, 
        {
            "room": "FA203", 
            "prof": "Petra Mehl", 
            "time": "08:00-15:30", 
            "name": "Personalentwicklung und beratung in globalen Unternehmen", 
            "type": "HF:0"
        }, 
        {
            "room": "FA013", 
            "prof": "Dr. Robin M\u00fcller", 
            "time": "08:00-15:30", 
            "name": "Personalentwicklung und beratung in globalen Unternehmen", 
            "type": "HF:0"
        }, 
        {
            "room": "FD246", 
            "prof": "Petra Mehl", 
            "time": "08:00-17:15", 
            "name": "Interkulturelles Management", 
            "note": "(Gruppe I)", 
            "type": "HF:0"
        }, 
        {
            "room": "FA013", 
            "prof": "Petra Mehl", 
            "time": "08:00-15:30", 
            "name": "Interkulturelles Management", 
            "note": "(Gruppe II)", 
            "type": "HF:0"
        }, 
        {
            "room": "FA013", 
            "prof": "Petra Mehl", 
            "time": "08:00-15:30", 
            "name": "Interkulturelles Management", 
            "note": "(Gruppe I)", 
            "type": "HF:0"
        }
    ], 
    "Tuesday": [
        {
            "room": "Ex_Extern", 
            "prof": "Norbert Gebhardt", 
            "time": "09:00-17:00", 
            "name": "Personalentwicklung und beratung in globalen Unternehmen", 
            "type": "HF:0"
        }, 
        {
            "room": "FA204", 
            "prof": "Blockveranstaltung Fachsemester 2", 
            "time": "11:30-15:45", 
            "name": "Kommunikation, Gespr\u00e4chsf\u00fchrung und Konfliktmanagement", 
            "note": "(Gruppe II)", 
            "type": "HF:0"
        }, 
        {
            "room": "FA204", 
            "prof": "Blockveranstaltung Fachsemester 2", 
            "time": "11:30-15:45", 
            "name": "Kommunikation, Gespr\u00e4chsf\u00fchrung und Konfliktmanagement", 
            "note": "(Gruppe II)", 
            "type": "HF:0"
        }, 
        {
            "room": "FA204", 
            "prof": "Blockveranstaltung Fachsemester 2", 
            "time": "11:30-17:30", 
            "name": "Kommunikation, Gespr\u00e4chsf\u00fchrung und Konfliktmanagement", 
            "note": "(Gruppe II)", 
            "type": "HF:0"
        }, 
        {
            "room": "FA204", 
            "prof": "Blockveranstaltung Fachsemester 2", 
            "time": "11:30-17:30", 
            "name": "Kommunikation, Gespr\u00e4chsf\u00fchrung und Konfliktmanagement", 
            "note": "(Gruppe II)", 
            "type": "HF:0"
        }, 
        {
            "room": "FA204", 
            "prof": "Blockveranstaltung Fachsemester 1", 
            "time": "11:30-15:45", 
            "name": "Kommunikation, Gespr\u00e4chsf\u00fchrung und Konfliktmanagement", 
            "note": "(Gruppe I)", 
            "type": "HF:0"
        }, 
        {
            "room": "FA204", 
            "prof": "Blockveranstaltung Fachsemester 1", 
            "time": "11:30-17:30", 
            "name": "Kommunikation, Gespr\u00e4chsf\u00fchrung und Konfliktmanagement", 
            "note": "(Gruppe I)", 
            "type": "HF:0"
        }, 
        {
            "room": "FA204", 
            "prof": "Blockveranstaltung Fachsemester 1", 
            "time": "11:30-17:30", 
            "name": "Kommunikation, Gespr\u00e4chsf\u00fchrung und Konfliktmanagement", 
            "note": "(Gruppe I)", 
            "type": "HF:0"
        }, 
        {
            "room": "FA204", 
            "prof": "Blockveranstaltung Fachsemester 2", 
            "time": "11:30-15:45", 
            "name": "Kommunikation, Gespr\u00e4chsf\u00fchrung und Konfliktmanagement", 
            "note": "(Gruppe II)", 
            "type": "HF:0"
        }, 
        {
            "room": "FA204", 
            "prof": "Blockveranstaltung Fachsemester 1", 
            "time": "11:30-15:45", 
            "name": "Kommunikation, Gespr\u00e4chsf\u00fchrung und Konfliktmanagement", 
            "note": "(Gruppe I)", 
            "type": "HF:0"
        }, 
        {
            "room": "FA204", 
            "prof": "Blockveranstaltung Fachsemester 1", 
            "time": "11:30-15:45", 
            "name": "Kommunikation, Gespr\u00e4chsf\u00fchrung und Konfliktmanagement", 
            "note": "(Gruppe I)", 
            "type": "HF:0"
        }
    ], 
    "Wednesday": [
        {
            "room": "FA201", 
            "prof": "Prof. Dr. Peter Sch\u00e4fer", 
            "time": "08:00-09:30", 
            "name": "Europ\u00e4isches Arbeitsrecht", 
            "type": "HF:0"
        }, 
        {
            "room": "FA103", 
            "prof": "Prof. Dr. J\u00fcrgen Kemper", 
            "time": "09:45-11:15", 
            "name": "Individualarbeitsrecht", 
            "type": "HF:0"
        }, 
        {
            "room": "FA103", 
            "prof": "Prof. Dr. Beatrix Weber", 
            "time": "11:30-13:00", 
            "name": "Compliance im Arbeitsrecht", 
            "type": "HF:0"
        }, 
        {
            "room": "FD175", 
            "prof": "Prof. Dr. Matthias Mungenast", 
            "time": "14:00-15:30", 
            "name": "Personalauswahl und Personalmarketing", 
            "type": "HF:0"
        }, 
        {
            "room": "FA201", 
            "prof": "Prof. Dr. Dietmar Boerner", 
            "time": "15:45-17:15", 
            "name": "Informationsveranstaltung", 
            "type": "HF:0"
        }, 
        {
            "room": "FA014", 
            "prof": "Prof. Dr. Dietmar Boerner", 
            "time": "17:30-19:00", 
            "name": "Informationsveranstaltung", 
            "type": "HF:0"
        }
    ], 
    "Thursday": [
        {
            "room": "FA103", 
            "prof": "Prof. Dr. J\u00fcrgen Kemper", 
            "time": "09:45-11:15", 
            "name": "Individualarbeitsrecht", 
            "type": "HF:0"
        }, 
        {
            "room": "FA103", 
            "prof": "Prof. Dr. Dietmar Boerner", 
            "time": "11:30-13:00", 
            "name": "Sozialrecht", 
            "type": "HF:0"
        }, 
        {
            "room": "FA103", 
            "prof": "Prof. Dr. Dietmar Boerner", 
            "time": "14:00-15:30", 
            "name": "Sozialrecht", 
            "type": "HF:0"
        }
    ]
}